{"nodes": [{"id": "frontend_react_src_pages_therapist_jsx", "label": "Therapist.jsx", "file_type": "code", "source_file": "frontend-react\\src\\pages\\Therapist.jsx", "source_location": "L1"}, {"id": "therapist_getsessionid", "label": "getSessionId()", "file_type": "code", "source_file": "frontend-react\\src\\pages\\Therapist.jsx", "source_location": "L31"}, {"id": "therapist_logpeerstate", "label": "logPeerState()", "file_type": "code", "source_file": "frontend-react\\src\\pages\\Therapist.jsx", "source_location": "L36"}, {"id": "therapist_attachstreamtovideo", "label": "attachStreamToVideo()", "file_type": "code", "source_file": "frontend-react\\src\\pages\\Therapist.jsx", "source_location": "L43"}, {"id": "therapist_pad", "label": "pad()", "file_type": "code", "source_file": "frontend-react\\src\\pages\\Therapist.jsx", "source_location": "L81"}, {"id": "therapist_formatnow", "label": "formatNow()", "file_type": "code", "source_file": "frontend-react\\src\\pages\\Therapist.jsx", "source_location": "L85"}, {"id": "therapist_gettopemotion", "label": "getTopEmotion()", "file_type": "code", "source_file": "frontend-react\\src\\pages\\Therapist.jsx", "source_location": "L90"}, {"id": "therapist_drawemotiontag", "label": "drawEmotionTag()", "file_type": "code", "source_file": "frontend-react\\src\\pages\\Therapist.jsx", "source_location": "L131"}, {"id": "therapist_withtimeout", "label": "withTimeout()", "file_type": "code", "source_file": "frontend-react\\src\\pages\\Therapist.jsx", "source_location": "L150"}, {"id": "therapist_checkurl", "label": "checkUrl()", "file_type": "code", "source_file": "frontend-react\\src\\pages\\Therapist.jsx", "source_location": "L159"}, {"id": "therapist_resolvefaceapiendpoints", "label": "resolveFaceApiEndpoints()", "file_type": "code", "source_file": "frontend-react\\src\\pages\\Therapist.jsx", "source_location": "L168"}, {"id": "therapist_ensurefaceapiloaded", "label": "ensureFaceApiLoaded()", "file_type": "code", "source_file": "frontend-react\\src\\pages\\Therapist.jsx", "source_location": "L192"}, {"id": "therapist_therapist", "label": "Therapist()", "file_type": "code", "source_file": "frontend-react\\src\\pages\\Therapist.jsx", "source_location": "L215"}], "edges": [{"source": "frontend_react_src_pages_therapist_jsx", "target": "react", "relation": "imports_from", "confidence": "EXTRACTED", "source_file": "frontend-react\\src\\pages\\Therapist.jsx", "source_location": "L1", "weight": 1.0}, {"source": "frontend_react_src_pages_therapist_jsx", "target": "socket_io_client", "relation": "imports_from", "confidence": "EXTRACTED", "source_file": "frontend-react\\src\\pages\\Therapist.jsx", "source_location": "L2", "weight": 1.0}, {"source": "frontend_react_src_pages_therapist_jsx", "target": "react_router_dom", "relation": "imports_from", "confidence": "EXTRACTED", "source_file": "frontend-react\\src\\pages\\Therapist.jsx", "source_location": "L3", "weight": 1.0}, {"source": "frontend_react_src_pages_therapist_jsx", "target": "firestore", "relation": "imports_from", "confidence": "EXTRACTED", "source_file": "frontend-react\\src\\pages\\Therapist.jsx", "source_location": "L4", "weight": 1.0}, {"source": "frontend_react_src_pages_therapist_jsx", "target": "frontend_react_src_components_calltopbar", "relation": "imports_from", "confidence": "EXTRACTED", "source_file": "frontend-react\\src\\pages\\Therapist.jsx", "source_location": "L5", "weight": 1.0}, {"source": "frontend_react_src_pages_therapist_jsx", "target": "frontend_react_src_layout_sidebar", "relation": "imports_from", "confidence": "EXTRACTED", "source_file": "frontend-react\\src\\pages\\Therapist.jsx", "source_location": "L6", "weight": 1.0}, {"source": "frontend_react_src_pages_therapist_jsx", "target": "frontend_react_src_components_emotionpanel", "relation": "imports_from", "confidence": "EXTRACTED", "source_file": "frontend-react\\src\\pages\\Therapist.jsx", "source_location": "L7", "weight": 1.0}, {"source": "frontend_react_src_pages_therapist_jsx", "target": "frontend_react_src_components_graph", "relation": "imports_from", "confidence": "EXTRACTED", "source_file": "frontend-react\\src\\pages\\Therapist.jsx", "source_location": "L8", "weight": 1.0}, {"source": "frontend_react_src_pages_therapist_jsx", "target": "frontend_react_src_components_sessionreportcard", "relation": "imports_from", "confidence": "EXTRACTED", "source_file": "frontend-react\\src\\pages\\Therapist.jsx", "source_location": "L9", "weight": 1.0}, {"source": "frontend_react_src_pages_therapist_jsx", "target": "frontend_react_src_components_videocontrols", "relation": "imports_from", "confidence": "EXTRACTED", "source_file": "frontend-react\\src\\pages\\Therapist.jsx", "source_location": "L10", "weight": 1.0}, {"source": "frontend_react_src_pages_therapist_jsx", "target": "frontend_react_src_hooks_usedraggablepip", "relation": "imports_from", "confidence": "EXTRACTED", "source_file": "frontend-react\\src\\pages\\Therapist.jsx", "source_location": "L11", "weight": 1.0}, {"source": "frontend_react_src_pages_therapist_jsx", "target": "frontend_react_src_utils_generatepdf", "relation": "imports_from", "confidence": "EXTRACTED", "source_file": "frontend-react\\src\\pages\\Therapist.jsx", "source_location": "L12", "weight": 1.0}, {"source": "frontend_react_src_pages_therapist_jsx", "target": "frontend_react_src_utils_reportbuilder", "relation": "imports_from", "confidence": "EXTRACTED", "source_file": "frontend-react\\src\\pages\\Therapist.jsx", "source_location": "L13", "weight": 1.0}, {"source": "frontend_react_src_pages_therapist_jsx", "target": "frontend_react_src_utils_sessionanalytics", "relation": "imports_from", "confidence": "EXTRACTED", "source_file": "frontend-react\\src\\pages\\Therapist.jsx", "source_location": "L14", "weight": 1.0}, {"source": "frontend_react_src_pages_therapist_jsx", "target": "frontend_react_src_lib_firebase", "relation": "imports_from", "confidence": "EXTRACTED", "source_file": "frontend-react\\src\\pages\\Therapist.jsx", "source_location": "L15", "weight": 1.0}, {"source": "frontend_react_src_pages_therapist_jsx", "target": "therapist_getsessionid", "relation": "contains", "confidence": "EXTRACTED", "source_file": "frontend-react\\src\\pages\\Therapist.jsx", "source_location": "L31", "weight": 1.0}, {"source": "frontend_react_src_pages_therapist_jsx", "target": "therapist_logpeerstate", "relation": "contains", "confidence": "EXTRACTED", "source_file": "frontend-react\\src\\pages\\Therapist.jsx", "source_location": "L36", "weight": 1.0}, {"source": "frontend_react_src_pages_therapist_jsx", "target": "therapist_attachstreamtovideo", "relation": "contains", "confidence": "EXTRACTED", "source_file": "frontend-react\\src\\pages\\Therapist.jsx", "source_location": "L43", "weight": 1.0}, {"source": "frontend_react_src_pages_therapist_jsx", "target": "therapist_pad", "relation": "contains", "confidence": "EXTRACTED", "source_file": "frontend-react\\src\\pages\\Therapist.jsx", "source_location": "L81", "weight": 1.0}, {"source": "frontend_react_src_pages_therapist_jsx", "target": "therapist_formatnow", "relation": "contains", "confidence": "EXTRACTED", "source_file": "frontend-react\\src\\pages\\Therapist.jsx", "source_location": "L85", "weight": 1.0}, {"source": "frontend_react_src_pages_therapist_jsx", "target": "therapist_gettopemotion", "relation": "contains", "confidence": "EXTRACTED", "source_file": "frontend-react\\src\\pages\\Therapist.jsx", "source_location": "L90", "weight": 1.0}, {"source": "frontend_react_src_pages_therapist_jsx", "target": "therapist_drawemotiontag", "relation": "contains", "confidence": "EXTRACTED", "source_file": "frontend-react\\src\\pages\\Therapist.jsx", "source_location": "L131", "weight": 1.0}, {"source": "frontend_react_src_pages_therapist_jsx", "target": "therapist_withtimeout", "relation": "contains", "confidence": "EXTRACTED", "source_file": "frontend-react\\src\\pages\\Therapist.jsx", "source_location": "L150", "weight": 1.0}, {"source": "frontend_react_src_pages_therapist_jsx", "target": "therapist_checkurl", "relation": "contains", "confidence": "EXTRACTED", "source_file": "frontend-react\\src\\pages\\Therapist.jsx", "source_location": "L159", "weight": 1.0}, {"source": "frontend_react_src_pages_therapist_jsx", "target": "therapist_resolvefaceapiendpoints", "relation": "contains", "confidence": "EXTRACTED", "source_file": "frontend-react\\src\\pages\\Therapist.jsx", "source_location": "L168", "weight": 1.0}, {"source": "frontend_react_src_pages_therapist_jsx", "target": "therapist_ensurefaceapiloaded", "relation": "contains", "confidence": "EXTRACTED", "source_file": "frontend-react\\src\\pages\\Therapist.jsx", "source_location": "L192", "weight": 1.0}, {"source": "frontend_react_src_pages_therapist_jsx", "target": "therapist_therapist", "relation": "contains", "confidence": "EXTRACTED", "source_file": "frontend-react\\src\\pages\\Therapist.jsx", "source_location": "L215", "weight": 1.0}, {"source": "therapist_formatnow", "target": "therapist_pad", "relation": "calls", "confidence": "EXTRACTED", "source_file": "frontend-react\\src\\pages\\Therapist.jsx", "source_location": "L87", "weight": 1.0}, {"source": "therapist_resolvefaceapiendpoints", "target": "therapist_checkurl", "relation": "calls", "confidence": "EXTRACTED", "source_file": "frontend-react\\src\\pages\\Therapist.jsx", "source_location": "L175", "weight": 1.0}], "raw_calls": [{"caller_nid": "therapist_getsessionid", "callee": "getItem", "source_file": "frontend-react\\src\\pages\\Therapist.jsx", "source_location": "L33"}, {"caller_nid": "therapist_getsessionid", "callee": "get", "source_file": "frontend-react\\src\\pages\\Therapist.jsx", "source_location": "L33"}, {"caller_nid": "therapist_logpeerstate", "callee": "log", "source_file": "frontend-react\\src\\pages\\Therapist.jsx", "source_location": "L37"}, {"caller_nid": "therapist_logpeerstate", "callee": "log", "source_file": "frontend-react\\src\\pages\\Therapist.jsx", "source_location": "L38"}, {"caller_nid": "therapist_logpeerstate", "callee": "log", "source_file": "frontend-react\\src\\pages\\Therapist.jsx", "source_location": "L39"}, {"caller_nid": "therapist_logpeerstate", "callee": "log", "source_file": "frontend-react\\src\\pages\\Therapist.jsx", "source_location": "L40"}, {"caller_nid": "therapist_attachstreamtovideo", "callee": "log", "source_file": "frontend-react\\src\\pages\\Therapist.jsx", "source_location": "L47"}, {"caller_nid": "therapist_attachstreamtovideo", "callee": "catch", "source_file": "frontend-react\\src\\pages\\Therapist.jsx", "source_location": "L48"}, {"caller_nid": "therapist_attachstreamtovideo", "callee": "then", "source_file": "frontend-react\\src\\pages\\Therapist.jsx", "source_location": "L48"}, {"caller_nid": "therapist_attachstreamtovideo", "callee": "play", "source_file": "frontend-react\\src\\pages\\Therapist.jsx", "source_location": "L48"}, {"caller_nid": "therapist_pad", "callee": "padStart", "source_file": "frontend-react\\src\\pages\\Therapist.jsx", "source_location": "L82"}, {"caller_nid": "therapist_pad", "callee": "String", "source_file": "frontend-react\\src\\pages\\Therapist.jsx", "source_location": "L82"}, {"caller_nid": "therapist_formatnow", "callee": "getHours", "source_file": "frontend-react\\src\\pages\\Therapist.jsx", "source_location": "L87"}, {"caller_nid": "therapist_formatnow", "callee": "getMinutes", "source_file": "frontend-react\\src\\pages\\Therapist.jsx", "source_location": "L87"}, {"caller_nid": "therapist_formatnow", "callee": "getSeconds", "source_file": "frontend-react\\src\\pages\\Therapist.jsx", "source_location": "L87"}, {"caller_nid": "therapist_gettopemotion", "callee": "map", "source_file": "frontend-react\\src\\pages\\Therapist.jsx", "source_location": "L93"}, {"caller_nid": "therapist_gettopemotion", "callee": "filter", "source_file": "frontend-react\\src\\pages\\Therapist.jsx", "source_location": "L93"}, {"caller_nid": "therapist_gettopemotion", "callee": "entries", "source_file": "frontend-react\\src\\pages\\Therapist.jsx", "source_location": "L93"}, {"caller_nid": "therapist_gettopemotion", "callee": "find", "source_file": "frontend-react\\src\\pages\\Therapist.jsx", "source_location": "L107"}, {"caller_nid": "therapist_gettopemotion", "callee": "find", "source_file": "frontend-react\\src\\pages\\Therapist.jsx", "source_location": "L108"}, {"caller_nid": "therapist_gettopemotion", "callee": "find", "source_file": "frontend-react\\src\\pages\\Therapist.jsx", "source_location": "L109"}, {"caller_nid": "therapist_gettopemotion", "callee": "find", "source_file": "frontend-react\\src\\pages\\Therapist.jsx", "source_location": "L110"}, {"caller_nid": "therapist_drawemotiontag", "callee": "measureText", "source_file": "frontend-react\\src\\pages\\Therapist.jsx", "source_location": "L137"}, {"caller_nid": "therapist_drawemotiontag", "callee": "fillRect", "source_file": "frontend-react\\src\\pages\\Therapist.jsx", "source_location": "L145"}, {"caller_nid": "therapist_drawemotiontag", "callee": "fillText", "source_file": "frontend-react\\src\\pages\\Therapist.jsx", "source_location": "L147"}, {"caller_nid": "therapist_withtimeout", "callee": "race", "source_file": "frontend-react\\src\\pages\\Therapist.jsx", "source_location": "L151"}, {"caller_nid": "therapist_checkurl", "callee": "fetch", "source_file": "frontend-react\\src\\pages\\Therapist.jsx", "source_location": "L161"}, {"caller_nid": "therapist_therapist", "callee": "useNavigate", "source_file": "frontend-react\\src\\pages\\Therapist.jsx", "source_location": "L216"}, {"caller_nid": "therapist_therapist", "callee": "useLocation", "source_file": "frontend-react\\src\\pages\\Therapist.jsx", "source_location": "L217"}, {"caller_nid": "therapist_therapist", "callee": "useRef", "source_file": "frontend-react\\src\\pages\\Therapist.jsx", "source_location": "L218"}, {"caller_nid": "therapist_therapist", "callee": "useRef", "source_file": "frontend-react\\src\\pages\\Therapist.jsx", "source_location": "L219"}, {"caller_nid": "therapist_therapist", "callee": "useRef", "source_file": "frontend-react\\src\\pages\\Therapist.jsx", "source_location": "L220"}, {"caller_nid": "therapist_therapist", "callee": "useRef", "source_file": "frontend-react\\src\\pages\\Therapist.jsx", "source_location": "L221"}, {"caller_nid": "therapist_therapist", "callee": "useRef", "source_file": "frontend-react\\src\\pages\\Therapist.jsx", "source_location": "L222"}, {"caller_nid": "therapist_therapist", "callee": "useRef", "source_file": "frontend-react\\src\\pages\\Therapist.jsx", "source_location": "L223"}, {"caller_nid": "therapist_therapist", "callee": "useRef", "source_file": "frontend-react\\src\\pages\\Therapist.jsx", "source_location": "L224"}, {"caller_nid": "therapist_therapist", "callee": "useRef", "source_file": "frontend-react\\src\\pages\\Therapist.jsx", "source_location": "L225"}, {"caller_nid": "therapist_therapist", "callee": "useRef", "source_file": "frontend-react\\src\\pages\\Therapist.jsx", "source_location": "L226"}, {"caller_nid": "therapist_therapist", "callee": "useRef", "source_file": "frontend-react\\src\\pages\\Therapist.jsx", "source_location": "L227"}, {"caller_nid": "therapist_therapist", "callee": "useRef", "source_file": "frontend-react\\src\\pages\\Therapist.jsx", "source_location": "L228"}, {"caller_nid": "therapist_therapist", "callee": "useRef", "source_file": "frontend-react\\src\\pages\\Therapist.jsx", "source_location": "L229"}, {"caller_nid": "therapist_therapist", "callee": "useRef", "source_file": "frontend-react\\src\\pages\\Therapist.jsx", "source_location": "L230"}, {"caller_nid": "therapist_therapist", "callee": "useRef", "source_file": "frontend-react\\src\\pages\\Therapist.jsx", "source_location": "L231"}, {"caller_nid": "therapist_therapist", "callee": "useRef", "source_file": "frontend-react\\src\\pages\\Therapist.jsx", "source_location": "L232"}, {"caller_nid": "therapist_therapist", "callee": "useRef", "source_file": "frontend-react\\src\\pages\\Therapist.jsx", "source_location": "L233"}, {"caller_nid": "therapist_therapist", "callee": "useRef", "source_file": "frontend-react\\src\\pages\\Therapist.jsx", "source_location": "L234"}, {"caller_nid": "therapist_therapist", "callee": "useRef", "source_file": "frontend-react\\src\\pages\\Therapist.jsx", "source_location": "L235"}, {"caller_nid": "therapist_therapist", "callee": "useRef", "source_file": "frontend-react\\src\\pages\\Therapist.jsx", "source_location": "L236"}, {"caller_nid": "therapist_therapist", "callee": "useRef", "source_file": "frontend-react\\src\\pages\\Therapist.jsx", "source_location": "L237"}, {"caller_nid": "therapist_therapist", "callee": "useRef", "source_file": "frontend-react\\src\\pages\\Therapist.jsx", "source_location": "L238"}, {"caller_nid": "therapist_therapist", "callee": "useRef", "source_file": "frontend-react\\src\\pages\\Therapist.jsx", "source_location": "L239"}, {"caller_nid": "therapist_therapist", "callee": "useRef", "source_file": "frontend-react\\src\\pages\\Therapist.jsx", "source_location": "L240"}, {"caller_nid": "therapist_therapist", "callee": "useRef", "source_file": "frontend-react\\src\\pages\\Therapist.jsx", "source_location": "L241"}, {"caller_nid": "therapist_therapist", "callee": "useRef", "source_file": "frontend-react\\src\\pages\\Therapist.jsx", "source_location": "L242"}, {"caller_nid": "therapist_therapist", "callee": "useRef", "source_file": "frontend-react\\src\\pages\\Therapist.jsx", "source_location": "L243"}, {"caller_nid": "therapist_therapist", "callee": "useRef", "source_file": "frontend-react\\src\\pages\\Therapist.jsx", "source_location": "L244"}, {"caller_nid": "therapist_therapist", "callee": "useRef", "source_file": "frontend-react\\src\\pages\\Therapist.jsx", "source_location": "L245"}, {"caller_nid": "therapist_therapist", "callee": "useRef", "source_file": "frontend-react\\src\\pages\\Therapist.jsx", "source_location": "L246"}, {"caller_nid": "therapist_therapist", "callee": "useRef", "source_file": "frontend-react\\src\\pages\\Therapist.jsx", "source_location": "L247"}, {"caller_nid": "therapist_therapist", "callee": "useRef", "source_file": "frontend-react\\src\\pages\\Therapist.jsx", "source_location": "L248"}, {"caller_nid": "therapist_therapist", "callee": "useState", "source_file": "frontend-react\\src\\pages\\Therapist.jsx", "source_location": "L250"}, {"caller_nid": "therapist_therapist", "callee": "useState", "source_file": "frontend-react\\src\\pages\\Therapist.jsx", "source_location": "L251"}, {"caller_nid": "therapist_therapist", "callee": "useState", "source_file": "frontend-react\\src\\pages\\Therapist.jsx", "source_location": "L252"}, {"caller_nid": "therapist_therapist", "callee": "useState", "source_file": "frontend-react\\src\\pages\\Therapist.jsx", "source_location": "L253"}, {"caller_nid": "therapist_therapist", "callee": "useState", "source_file": "frontend-react\\src\\pages\\Therapist.jsx", "source_location": "L254"}, {"caller_nid": "therapist_therapist", "callee": "useState", "source_file": "frontend-react\\src\\pages\\Therapist.jsx", "source_location": "L255"}, {"caller_nid": "therapist_therapist", "callee": "useState", "source_file": "frontend-react\\src\\pages\\Therapist.jsx", "source_location": "L256"}, {"caller_nid": "therapist_therapist", "callee": "useState", "source_file": "frontend-react\\src\\pages\\Therapist.jsx", "source_location": "L257"}, {"caller_nid": "therapist_therapist", "callee": "useState", "source_file": "frontend-react\\src\\pages\\Therapist.jsx", "source_location": "L258"}, {"caller_nid": "therapist_therapist", "callee": "useState", "source_file": "frontend-react\\src\\pages\\Therapist.jsx", "source_location": "L259"}, {"caller_nid": "therapist_therapist", "callee": "useState", "source_file": "frontend-react\\src\\pages\\Therapist.jsx", "source_location": "L260"}, {"caller_nid": "therapist_therapist", "callee": "useState", "source_file": "frontend-react\\src\\pages\\Therapist.jsx", "source_location": "L261"}, {"caller_nid": "therapist_therapist", "callee": "useState", "source_file": "frontend-react\\src\\pages\\Therapist.jsx", "source_location": "L265"}, {"caller_nid": "therapist_therapist", "callee": "useState", "source_file": "frontend-react\\src\\pages\\Therapist.jsx", "source_location": "L266"}, {"caller_nid": "therapist_therapist", "callee": "useState", "source_file": "frontend-react\\src\\pages\\Therapist.jsx", "source_location": "L267"}, {"caller_nid": "therapist_therapist", "callee": "useState", "source_file": "frontend-react\\src\\pages\\Therapist.jsx", "source_location": "L268"}, {"caller_nid": "therapist_therapist", "callee": "useState", "source_file": "frontend-react\\src\\pages\\Therapist.jsx", "source_location": "L269"}, {"caller_nid": "therapist_therapist", "callee": "useState", "source_file": "frontend-react\\src\\pages\\Therapist.jsx", "source_location": "L270"}, {"caller_nid": "therapist_therapist", "callee": "useState", "source_file": "frontend-react\\src\\pages\\Therapist.jsx", "source_location": "L271"}, {"caller_nid": "therapist_therapist", "callee": "useState", "source_file": "frontend-react\\src\\pages\\Therapist.jsx", "source_location": "L272"}, {"caller_nid": "therapist_therapist", "callee": "useState", "source_file": "frontend-react\\src\\pages\\Therapist.jsx", "source_location": "L273"}, {"caller_nid": "therapist_therapist", "callee": "useState", "source_file": "frontend-react\\src\\pages\\Therapist.jsx", "source_location": "L274"}, {"caller_nid": "therapist_therapist", "callee": "useState", "source_file": "frontend-react\\src\\pages\\Therapist.jsx", "source_location": "L275"}, {"caller_nid": "therapist_therapist", "callee": "useState", "source_file": "frontend-react\\src\\pages\\Therapist.jsx", "source_location": "L279"}, {"caller_nid": "therapist_therapist", "callee": "useDraggablePip", "source_file": "frontend-react\\src\\pages\\Therapist.jsx", "source_location": "L286"}, {"caller_nid": "therapist_therapist", "callee": "useMemo", "source_file": "frontend-react\\src\\pages\\Therapist.jsx", "source_location": "L288"}, {"caller_nid": "therapist_therapist", "callee": "useMemo", "source_file": "frontend-react\\src\\pages\\Therapist.jsx", "source_location": "L289"}, {"caller_nid": "therapist_therapist", "callee": "useMemo", "source_file": "frontend-react\\src\\pages\\Therapist.jsx", "source_location": "L290"}, {"caller_nid": "therapist_therapist", "callee": "useMemo", "source_file": "frontend-react\\src\\pages\\Therapist.jsx", "source_location": "L291"}, {"caller_nid": "therapist_therapist", "callee": "useMemo", "source_file": "frontend-react\\src\\pages\\Therapist.jsx", "source_location": "L292"}, {"caller_nid": "therapist_therapist", "callee": "useMemo", "source_file": "frontend-react\\src\\pages\\Therapist.jsx", "source_location": "L293"}, {"caller_nid": "therapist_therapist", "callee": "useEffect", "source_file": "frontend-react\\src\\pages\\Therapist.jsx", "source_location": "L295"}, {"caller_nid": "therapist_therapist", "callee": "useEffect", "source_file": "frontend-react\\src\\pages\\Therapist.jsx", "source_location": "L299"}, {"caller_nid": "therapist_therapist", "callee": "useEffect", "source_file": "frontend-react\\src\\pages\\Therapist.jsx", "source_location": "L318"}, {"caller_nid": "therapist_therapist", "callee": "useEffect", "source_file": "frontend-react\\src\\pages\\Therapist.jsx", "source_location": "L343"}, {"caller_nid": "therapist_therapist", "callee": "useEffect", "source_file": "frontend-react\\src\\pages\\Therapist.jsx", "source_location": "L347"}, {"caller_nid": "therapist_therapist", "callee": "useEffect", "source_file": "frontend-react\\src\\pages\\Therapist.jsx", "source_location": "L351"}, {"caller_nid": "therapist_therapist", "callee": "useEffect", "source_file": "frontend-react\\src\\pages\\Therapist.jsx", "source_location": "L376"}, {"caller_nid": "therapist_therapist", "callee": "useMemo", "source_file": "frontend-react\\src\\pages\\Therapist.jsx", "source_location": "L416"}, {"caller_nid": "therapist_therapist", "callee": "useEffect", "source_file": "frontend-react\\src\\pages\\Therapist.jsx", "source_location": "L728"}, {"caller_nid": "therapist_therapist", "callee": "useEffect", "source_file": "frontend-react\\src\\pages\\Therapist.jsx", "source_location": "L778"}, {"caller_nid": "therapist_therapist", "callee": "map", "source_file": "frontend-react\\src\\pages\\Therapist.jsx", "source_location": "L1305"}, {"caller_nid": "therapist_therapist", "callee": "map", "source_file": "frontend-react\\src\\pages\\Therapist.jsx", "source_location": "L1433"}]}